bigsmiles/__init__.py
bigsmiles/config.py
bigsmiles/errors.py
bigsmiles/constructors/__init__.py
bigsmiles/constructors/constructor.py
bigsmiles/constructors/constructor_reaction.py
bigsmiles/constructors/constructor_str.py
bigsmiles/constructors/constructor_tokens.py
bigsmiles/constructors/tokenizer.py
bigsmiles/data_structures/__init__.py
bigsmiles/data_structures/aromatic_conversion.py
bigsmiles/data_structures/bigsmiles.py
bigsmiles/data_structures/molecular_formula.py
bigsmiles/data_structures/reaction.py
bigsmiles/data_structures/stereo_rules.py
bigsmiles/methods/__init__.py
bigsmiles/methods/display_methods/__init__.py
bigsmiles/methods/display_methods/tree_to_string.py
bigsmiles/methods/graph/__init__.py
bigsmiles/methods/graph/adjacency_list.py
bigsmiles/methods/graph/adjacency_matrix.py
bigsmiles/reference_data/__init__.py
bigsmiles/reference_data/chemical_data.py
bigsmiles/reference_data/elements_data.json
bigsmiles/validation/__init__.py
bigsmiles/validation/validation_bigsmiles_obj.py
bigsmiles/validation/validation_string.py
bigsmiles/validation/validation_tokens.py
bigsmiles-0.0.10.dist-info/LICENSE.txt
bigsmiles-0.0.10.dist-info/METADATA
bigsmiles-0.0.10.dist-info/WHEEL
bigsmiles-0.0.10.dist-info/top_level.txt
bigsmiles-0.0.10.dist-info/RECORD
