Metadata-Version: 2.1
Name: bigsmiles
Version: 0.0.10
Summary: BigSMILES Parser
Home-page: https://github.com/dylanwal/bigsmiles
Author: Dylan Walsh
License: BSD
Platform: any
Classifier: License :: OSI Approved :: BSD License
Classifier: Programming Language :: Python :: 3
Classifier: Programming Language :: Python :: 3 :: Only
Classifier: Programming Language :: Python :: 3.7
Requires-Python: >=3.7
License-File: LICENSE.txt
